schimpy/Interp2D.py
schimpy/__init__.py
schimpy/_version.py
schimpy/base_io.py
schimpy/batch_metrics.py
schimpy/bay_delta_hotstart.py
schimpy/bctide.py
schimpy/bound_linear.py
schimpy/cencoos_download.py
schimpy/check_mesh_skewness.py
schimpy/clip_dems.py
schimpy/combine_consume.py
schimpy/combine_flux.py
schimpy/contour_smooth.py
schimpy/convert_linestrings.py
schimpy/convert_mesh.py
schimpy/convert_polygons.py
schimpy/convert_sav_class_to_number.py
schimpy/create_mesh_n_levels.py
schimpy/create_vgrid_lsc2.py
schimpy/cruise.py
schimpy/cut_mesh.py
schimpy/download_hrrr.py
schimpy/embed_raster.py
schimpy/gaussian_quadrature.py
schimpy/gen_elev2D.py
schimpy/geo_tools.py
schimpy/gr3.py
schimpy/grid_opt.py
schimpy/hotstart_inventory.py
schimpy/hrr3.py
schimpy/interpolate_structure.py
schimpy/laplace_smooth_data.py
schimpy/lsc2.py
schimpy/material_poly.py
schimpy/metricsplot.py
schimpy/model_time.py
schimpy/namelist.py
schimpy/nudging.py
schimpy/plot_default_formats.py
schimpy/polygons.py
schimpy/prepare_schism.py
schimpy/priority_queue.py
schimpy/profile_plot.py
schimpy/raster_to_nodes.py
schimpy/read_output_xyt.py
schimpy/schism_hotstart.py
schimpy/schism_input.py
schimpy/schism_linestring.py
schimpy/schism_mesh.py
schimpy/schism_nudging.py
schimpy/schism_polygon.py
schimpy/schism_setup.py
schimpy/schism_source.py
schimpy/schism_sources_sinks.py
schimpy/schism_structure.py
schimpy/schism_vertical_mesh.py
schimpy/schism_yaml.py
schimpy/separate_species.py
schimpy/simulation_timing.py
schimpy/small_areas.py
schimpy/sms2gr3.py
schimpy/split_quad.py
schimpy/stacked_dem_fill.py
schimpy/station.py
schimpy/subset_schism_output.py
schimpy/three_point_linear_norm.py
schimpy/trimesh.py
schimpy/triquadmesh.py
schimpy/unit_conversions.py
schimpy/vgrid_opt2.py
schimpy/write_ts.py
schimpy-1.4.3.dist-info/AUTHORS.rst
schimpy-1.4.3.dist-info/LICENSE
schimpy-1.4.3.dist-info/METADATA
schimpy-1.4.3.dist-info/WHEEL
schimpy-1.4.3.dist-info/entry_points.txt
schimpy-1.4.3.dist-info/top_level.txt
schimpy-1.4.3.dist-info/RECORD
