Metadata-Version: 2.1
Name: schimpy
Version: 1.4.3
Summary: Python package for SCHISM
Home-page: https://github.com/CADWRDeltaModeling/schimpy
Author: California Department of Water Resources
Author-email: Eli.Ateljevich@water.ca.gov, Kijin.Nam@water.ca.gov
License: MIT license
Keywords: schimpy
Classifier: Development Status :: 2 - Pre-Alpha
Classifier: Intended Audience :: Developers
Classifier: License :: OSI Approved :: MIT License
Classifier: Natural Language :: English
Classifier: Programming Language :: Python :: 3
Classifier: Programming Language :: Python :: 3.5
Classifier: Programming Language :: Python :: 3.6
Classifier: Programming Language :: Python :: 3.7
Classifier: Programming Language :: Python :: 3.8
Classifier: Programming Language :: Python :: 3.9
Requires-Python: >=3.5
License-File: LICENSE
License-File: AUTHORS.rst
Requires-Dist: geopandas
Requires-Dist: vtools3
Requires-Dist: xarray
Requires-Dist: netcdf4
Requires-Dist: scipy
Requires-Dist: matplotlib
Requires-Dist: statsmodels
Requires-Dist: palettable
Requires-Dist: pyyaml
Requires-Dist: scikit-learn
Requires-Dist: beautifulsoup4
Requires-Dist: pyproj
Requires-Dist: nodepy
Requires-Dist: shapely (<2.0)
Requires-Dist: rasterstats
